cm_tools/__init__.py
cm_tools/images.py
cm_tools-0.0.1.dist-info/DESCRIPTION.rst
cm_tools-0.0.1.dist-info/entry_points.txt
cm_tools-0.0.1.dist-info/METADATA
cm_tools-0.0.1.dist-info/metadata.json
cm_tools-0.0.1.dist-info/RECORD
cm_tools-0.0.1.dist-info/top_level.txt
cm_tools-0.0.1.dist-info/WHEEL
