Metadata-Version: 2.0
Name: cm-tools
Version: 0.0.1
Summary: CLI tools for working with CloudMan clusters
Home-page: https://github.com/simonalpha/cm_tools
Author: Simon Belluzzo
Author-email: simon@belluzzo.id.au
License: MIT
Platform: UNKNOWN
Classifier: Development Status :: 3 - Alpha
Classifier: Intended Audience :: Developers
Classifier: Intended Audience :: System Administrators
Classifier: License :: OSI Approved :: MIT License
Classifier: Programming Language :: Python :: 2
Requires-Dist: boto (<2.35.0)
Requires-Dist: bioblend
Requires-Dist: docopt
